[
    {
        "algoritmo": "heap_sort_500",
        "quantidade_palavras": 500,
        "tempo": 0.34375
    },
    {
        "algoritmo": "heap_sort_500",
        "quantidade_palavras": 500,
        "tempo": 0.34375
    },
    {
        "algoritmo": "heap_sort_500",
        "quantidade_palavras": 500,
        "tempo": 0.34375
    },
    {
        "algoritmo": "heap_sort_500",
        "quantidade_palavras": 500,
        "tempo": 0.328125
    },
    {
        "algoritmo": "heap_sort_500",
        "quantidade_palavras": 500,
        "tempo": 0.390625
    }
]